mujoco_maze/__init__.py
mujoco_maze/agent_model.py
mujoco_maze/ant.py
mujoco_maze/assets/ant.xml
mujoco_maze/assets/point.xml
mujoco_maze/assets/reacher.xml
mujoco_maze/assets/swimmer.xml
mujoco_maze/maze_env.py
mujoco_maze/maze_env_utils.py
mujoco_maze/maze_task.py
mujoco_maze/point.py
mujoco_maze/reacher.py
mujoco_maze/swimmer.py
mujoco_maze/websock_viewer.py
mujoco_maze-0.2.0.dist-info/entry_points.txt
mujoco_maze-0.2.0.dist-info/LICENSE
mujoco_maze-0.2.0.dist-info/WHEEL
mujoco_maze-0.2.0.dist-info/METADATA
mujoco_maze-0.2.0.dist-info/RECORD
