Metadata-Version: 2.1
Name: mujoco-maze
Version: 0.2.0
Summary: Simple maze environments using mujoco-py
Home-page: https://github.com/kngwyu/mujoco-maze
License: Apache-2.0
Author: Yuji Kanagawa
Author-email: yuji.kngw.80s.revive@gmail.com
Requires-Python: >=3.6
Classifier: License :: OSI Approved :: Apache Software License
Classifier: Programming Language :: Python :: 3
Classifier: Programming Language :: Python :: 3.6
Classifier: Programming Language :: Python :: 3.7
Classifier: Programming Language :: Python :: 3.8
Classifier: Programming Language :: Python :: 3.9
Requires-Dist: gym (>=0.16)
Requires-Dist: mujoco-py (>=1.5)
Project-URL: Repository, https://github.com/kngwyu/mujoco-maze
